cometpy/PyMLIRGen.py
cometpy/__init__.py
cometpy/comet.py
cometpy/lowering.py
cometpy/types_mlir.py
cometpy/utils.py
cometpy/comet_build/bin/comet-opt
cometpy/comet_build/lib/libcomet_runner_utils.dylib
cometpy/llvm_build/bin/lli
cometpy/llvm_build/bin/mlir-opt
cometpy/llvm_build/bin/mlir-translate
cometpy-0.1.dist-info/LICENSE
cometpy-0.1.dist-info/METADATA
cometpy-0.1.dist-info/WHEEL
cometpy-0.1.dist-info/top_level.txt
cometpy-0.1.dist-info/RECORD
