Metadata-Version: 2.1
Name: cometpy
Version: 0.1
Summary: Comet Domain Specific Compiler as Python package
Author: Gokcen Kestor
Author-email: gokcen.kestor@pnnl.gov
Classifier: Programming Language :: Python :: 3
Classifier: License :: OSI Approved :: MIT License
Requires-Python: >=3.6
License-File: LICENSE
